pyconiq/__init__.py
pyconiq/__version__.py
pyconiq/concepts.py
pyconiq/constants.py
pyconiq/exceptions.py
pyconiq/integrations/__init__.py
pyconiq/integrations/base.py
pyconiq/integrations/static.py
pyconiq/qr.py
pyconiq-0.0.3.dist-info/LICENSE
pyconiq-0.0.3.dist-info/METADATA
pyconiq-0.0.3.dist-info/WHEEL
pyconiq-0.0.3.dist-info/RECORD
