Metadata-Version: 2.1
Name: pyconiq
Version: 0.0.3
Summary: Unofficial Python package to interface with the payment processor Payconiq.
Author: Joeri Hermans
Author-email: joeri@peinser.com
Requires-Python: >=3.11,<4.0
Classifier: Programming Language :: Python :: 3
Classifier: Programming Language :: Python :: 3.11
Requires-Dist: aiohttp (>=3.9.0,<4.0.0)
Requires-Dist: qrcode (>=7.4.2,<8.0.0)
Requires-Dist: ujson (>=5.8.0,<6.0.0)
